sphinx_codeautolink/__init__.py
sphinx_codeautolink/parse.py
sphinx_codeautolink/warn.py
sphinx_codeautolink/extension/__init__.py
sphinx_codeautolink/extension/backref.py
sphinx_codeautolink/extension/block.py
sphinx_codeautolink/extension/cache.py
sphinx_codeautolink/extension/directive.py
sphinx_codeautolink/extension/resolve.py
sphinx_codeautolink/extension/translation.py
sphinx_codeautolink/locale/sphinx-codeautolink.pot
sphinx_codeautolink/locale/de/LC_MESSAGES/sphinx-codeautolink.mo
sphinx_codeautolink/locale/de/LC_MESSAGES/sphinx-codeautolink.po
sphinx_codeautolink/locale/es/LC_MESSAGES/sphinx-codeautolink.mo
sphinx_codeautolink/locale/es/LC_MESSAGES/sphinx-codeautolink.po
sphinx_codeautolink/locale/fi/LC_MESSAGES/sphinx-codeautolink.mo
sphinx_codeautolink/locale/fi/LC_MESSAGES/sphinx-codeautolink.po
sphinx_codeautolink/locale/fr/LC_MESSAGES/sphinx-codeautolink.mo
sphinx_codeautolink/locale/fr/LC_MESSAGES/sphinx-codeautolink.po
sphinx_codeautolink/locale/it/LC_MESSAGES/sphinx-codeautolink.mo
sphinx_codeautolink/locale/it/LC_MESSAGES/sphinx-codeautolink.po
sphinx_codeautolink/locale/nl/LC_MESSAGES/sphinx-codeautolink.mo
sphinx_codeautolink/locale/nl/LC_MESSAGES/sphinx-codeautolink.po
sphinx_codeautolink/locale/ru/LC_MESSAGES/sphinx-codeautolink.po
sphinx_codeautolink/locale/uk/LC_MESSAGES/sphinx-codeautolink.po
sphinx_codeautolink/static/sphinx-codeautolink.css
sphinx_codeautolink-0.17.5.dist-info/licenses/LICENSE
sphinx_codeautolink-0.17.5.dist-info/METADATA
sphinx_codeautolink-0.17.5.dist-info/WHEEL
sphinx_codeautolink-0.17.5.dist-info/top_level.txt
sphinx_codeautolink-0.17.5.dist-info/RECORD
