Metadata-Version: 2.4
Name: sphinx-codeautolink
Version: 0.17.5
Summary: Automatic links from code examples to reference documentation.
Author-email: Felix Hildén <felix.hilden@gmail.com>
Maintainer-email: Felix Hildén <felix.hilden@gmail.com>
Project-URL: homepage, https://pypi.org/project/sphinx-codeautolink
Project-URL: download, https://pypi.org/project/sphinx-codeautolink
Project-URL: source, https://github.com/felix-hilden/sphinx-codeautolink
Project-URL: issues, https://github.com/felix-hilden/sphinx-codeautolink/issues
Project-URL: documentation, https://sphinx-codeautolink.rtfd.org
Keywords: sphinx,extension,code,link
Classifier: Development Status :: 4 - Beta
Classifier: Framework :: Sphinx
Classifier: Framework :: Sphinx :: Extension
Classifier: Programming Language :: Python :: 3
Classifier: Programming Language :: Python :: 3 :: Only
Classifier: Programming Language :: Python :: 3.10
Classifier: Programming Language :: Python :: 3.11
Classifier: Programming Language :: Python :: 3.12
Classifier: Programming Language :: Python :: 3.13
Classifier: Topic :: Documentation
Classifier: Topic :: Documentation :: Sphinx
Classifier: Topic :: Software Development :: Documentation
Requires-Python: >=3.10
License-File: LICENSE
Requires-Dist: sphinx>=3.2.0
Requires-Dist: beautifulsoup4>=4.8.1
Provides-Extra: ipython
Requires-Dist: ipython!=8.7.0; extra == "ipython"
Dynamic: license-file
